recompute/__init__.py
recompute/bundle.py
recompute/cmd.py
recompute/config.py
recompute/instance.py
recompute/process.py
recompute/recompute.py
recompute/remote.py
recompute/utils.py
recompute-0.9.14.dist-info/LICENSE
recompute-0.9.14.dist-info/METADATA
recompute-0.9.14.dist-info/WHEEL
recompute-0.9.14.dist-info/entry_points.txt
recompute-0.9.14.dist-info/top_level.txt
recompute-0.9.14.dist-info/RECORD
