Metadata-Version: 2.1
Name: recompute
Version: 0.9.14
Summary: Remote Execution Framework
Home-page: https://github.com/suriyadeepan/recompute.py
Author: Suriyadeepan Ramamoorthy
Author-email: suriyadeepan.r@gmail.com
License: UNKNOWN
Platform: UNKNOWN
Classifier: Programming Language :: Python :: 3
Classifier: License :: OSI Approved :: MIT License
Classifier: Operating System :: OS Independent
Requires-Dist: prettytable
Requires-Dist: pipreqs
Requires-Dist: pytest
